defi_marketplace_py/__init__.py
defi_marketplace_py/cli_wrapper.py
defi_marketplace_py/constants.py
defi_marketplace_py/downloader.py
defi_marketplace_py/publisher.py
defi_marketplace_py/utils.py
defi_marketplace_py-0.1.1.dist-info/METADATA
defi_marketplace_py-0.1.1.dist-info/WHEEL
defi_marketplace_py-0.1.1.dist-info/top_level.txt
defi_marketplace_py-0.1.1.dist-info/RECORD
